odoo10_addon_shopinvader_demo_app-10.0.1.0.0.99.dev8-py3.8-nspkg.pth
odoo/addons/shopinvader_demo_app/README.rst
odoo/addons/shopinvader_demo_app/__init__.py
odoo/addons/shopinvader_demo_app/__manifest__.py
odoo/addons/shopinvader_demo_app/data/ir_export_product.xml
odoo/addons/shopinvader_demo_app/demo/product_brand_demo.xml
odoo/addons/shopinvader_demo_app/demo/product_product_demo.xml
odoo/addons/shopinvader_demo_app/i18n/shopinvader_demo_app.pot
odoo/addons/shopinvader_demo_app/readme/CONTRIBUTORS.rst
odoo/addons/shopinvader_demo_app/readme/DESCRIPTION.rst
odoo/addons/shopinvader_demo_app/static/description/index.html
odoo10_addon_shopinvader_demo_app-10.0.1.0.0.99.dev8.dist-info/METADATA
odoo10_addon_shopinvader_demo_app-10.0.1.0.0.99.dev8.dist-info/WHEEL
odoo10_addon_shopinvader_demo_app-10.0.1.0.0.99.dev8.dist-info/namespace_packages.txt
odoo10_addon_shopinvader_demo_app-10.0.1.0.0.99.dev8.dist-info/top_level.txt
odoo10_addon_shopinvader_demo_app-10.0.1.0.0.99.dev8.dist-info/RECORD
