Metadata-Version: 2.1
Name: odoo10-addon-shopinvader-demo-app
Version: 10.0.1.0.0.99.dev8
Summary: Shopinvader Demo App
Home-page: https://github.com/shopinvader/odoo-shopinvader
Author: Akretion
License: AGPL-3
Platform: UNKNOWN
Classifier: Programming Language :: Python
Classifier: Framework :: Odoo
Classifier: License :: OSI Approved :: GNU Affero General Public License v3
Requires-Python: ~=2.7
Requires-Dist: odoo10-addon-product-brand
Requires-Dist: odoo10-addon-shopinvader-algolia
Requires-Dist: odoo (<10.1dev,>=10.0)
